{
    "version": "5.5.0",
    "flags": {},
    "shapes": [
        {
            "label": "wall",
            "points": [
                [
                    247.421,
                    218.574
                ],
                [
                    261.944,
                    217.712
                ],
                [
                    259.107,
                    181.528
                ],
                [
                    303.509,
                    177.655
                ],
                [
                    302.518,
                    161.299
                ],
                [
                    114.573,
                    173.827
                ],
                [
                    106.57,
                    46.203
                ],
                [
                    88.49,
                    46.7
                ],
                [
                    109.459,
                    339.979
                ],
                [
                    270.453,
                    328.414
                ],
                [
                    266.448,
                    277.728
                ],
                [
                    251.445,
                    278.316
                ],
                [
                    254.577,
                    314.326
                ],
                [
                    126.189,
                    322.383
                ],
                [
                    116.118,
                    191.526
                ],
                [
                    245.532,
                    182.784
                ],
                [
                    247.421,
                    218.574
                ]
            ],
            "group_id": null,
            "description": "",
            "shape_type": "polygon",
            "flags": {},
            "mask": null
        },
        {
            "label": "wall",
            "points": [
                [
                    118.951,
                    464.576
                ],
                [
                    107.872,
                    465.717
                ],
                [
                    108.878,
                    480.097
                ],
                [
                    121.451,
                    479.401
                ],
                [
                    127.486,
                    547.394
                ],
                [
                    176.48,
                    544.334
                ],
                [
                    176.111,
                    539.055
                ],
                [
                    181.051,
                    539.075
                ],
                [
                    180.025,
                    529.635
                ],
                [
                    141.056,
                    532.177
                ],
                [
                    129.405,
                    368.174
                ],
                [
                    111.879,
                    368.668
                ],
                [
                    118.951,
                    464.576
                ]
            ],
            "group_id": null,
            "description": "",
            "shape_type": "polygon",
            "flags": {},
            "mask": null
        },
        {
            "label": "wall",
            "points": [
                [
                    27.084,
                    485.921
                ],
                [
                    58.462,
                    484.369
                ],
                [
                    57.83,
                    469.206
                ],
                [
                    42.453,
                    469.853
                ],
                [
                    36.293,
                    384.819
                ],
                [
                    19.498,
                    386.636
                ],
                [
                    27.084,
                    485.921
                ]
            ],
            "group_id": null,
            "description": "",
            "shape_type": "polygon",
            "flags": {},
            "mask": null
        },
        {
            "label": "wall",
            "points": [
                [
                    361.631,
                    156.3
                ],
                [
                    363.122,
                    174.92
                ],
                [
                    424.806,
                    169.85
                ],
                [
                    437.472,
                    356.402
                ],
                [
                    484.138,
                    352.95
                ],
                [
                    485.681,
                    372.323
                ],
                [
                    494.528,
                    371.705
                ],
                [
                    494.05,
                    367.577
                ],
                [
                    501.014,
                    367.09
                ],
                [
                    498.129,
                    336.651
                ],
                [
                    451.503,
                    340.668
                ],
                [
                    437.307,
                    143.064
                ],
                [
                    592.265,
                    132.985
                ],
                [
                    591.374,
                    117.538
                ],
                [
                    439.104,
                    128.185
                ],
                [
                    430.819,
                    23.225
                ],
                [
                    414.268,
                    24.571
                ],
                [
                    422.951,
                    151.444
                ],
                [
                    361.631,
                    156.3
                ]
            ],
            "group_id": null,
            "description": "",
            "shape_type": "polygon",
            "flags": {},
            "mask": null
        },
        {
            "label": "wall",
            "points": [
                [
                    443.536,
                    187.693
                ],
                [
                    496.133,
                    183.78
                ],
                [
                    498.777,
                    223.485
                ],
                [
                    446.91,
                    227.314
                ],
                [
                    454.502,
                    335.884
                ],
                [
                    521.318,
                    331.422
                ],
                [
                    521.968,
                    338.914
                ],
                [
                    596.102,
                    332.87
                ],
                [
                    598.092,
                    355.587
                ],
                [
                    603.471,
                    355.11
                ],
                [
                    600.924,
                    318.318
                ],
                [
                    461.248,
                    328.245
                ],
                [
                    454.627,
                    234.585
                ],
                [
                    576.849,
                    225.536
                ],
                [
                    580.671,
                    279.153
                ],
                [
                    596.931,
                    278.064
                ],
                [
                    592.655,
                    215.914
                ],
                [
                    506.969,
                    222.619
                ],
                [
                    503.37,
                    175.455
                ],
                [
                    443.183,
                    179.767
                ],
                [
                    443.536,
                    187.693
                ]
            ],
            "group_id": null,
            "description": "",
            "shape_type": "polygon",
            "flags": {},
            "mask": null
        },
        {
            "label": "wall",
            "points": [
                [
                    491.054,
                    441.182
                ],
                [
                    365.18,
                    449.563
                ],
                [
                    367.623,
                    490.789
                ],
                [
                    268.759,
                    498.095
                ],
                [
                    270.392,
                    523.303
                ],
                [
                    240.322,
                    525.405
                ],
                [
                    240.524,
                    534.276
                ],
                [
                    246.038,
                    533.891
                ],
                [
                    246.082,
                    539.01
                ],
                [
                    285.558,
                    536.731
                ],
                [
                    283.472,
                    510.641
                ],
                [
                    374.467,
                    504.945
                ],
                [
                    376.901,
                    536.099
                ],
                [
                    250.369,
                    544.204
                ],
                [
                    251.008,
                    551.585
                ],
                [
                    275.64,
                    549.863
                ],
                [
                    281.653,
                    634.093
                ],
                [
                    255.914,
                    635.893
                ],
                [
                    256.275,
                    641.065
                ],
                [
                    281.769,
                    639.283
                ],
                [
                    281.967,
                    642.115
                ],
                [
                    289.207,
                    641.238
                ],
                [
                    282.482,
                    550.374
                ],
                [
                    377.39,
                    544.852
                ],
                [
                    387.6,
                    700.229
                ],
                [
                    293.42,
                    706.394
                ],
                [
                    292.224,
                    682.118
                ],
                [
                    284.915,
                    682.502
                ],
                [
                    286.224,
                    706.697
                ],
                [
                    265.767,
                    708.027
                ],
                [
                    266.172,
                    718.123
                ],
                [
                    388.366,
                    709.688
                ],
                [
                    403.647,
                    919.247
                ],
                [
                    360.151,
                    922.079
                ],
                [
                    361.266,
                    936.531
                ],
                [
                    446.223,
                    930.172
                ],
                [
                    445.495,
                    915.275
                ],
                [
                    419.83,
                    917.488
                ],
                [
                    414.33,
                    844.806
                ],
                [
                    515.334,
                    837.743
                ],
                [
                    517.803,
                    871.543
                ],
                [
                    528.212,
                    870.92
                ],
                [
                    525.302,
                    829.311
                ],
                [
                    414.157,
                    836.352
                ],
                [
                    395.126,
                    564.063
                ],
                [
                    434.349,
                    561.118
                ],
                [
                    433.733,
                    553.762
                ],
                [
                    394.684,
                    556.29
                ],
                [
                    389.935,
                    489.961
                ],
                [
                    382.52,
                    490.061
                ],
                [
                    380.851,
                    463.209
                ],
                [
                    506.821,
                    454.4
                ],
                [
                    505.497,
                    435.469
                ],
                [
                    498.632,
                    435.949
                ],
                [
                    498.222,
                    431.587
                ],
                [
                    490.295,
                    431.828
                ],
                [
                    491.054,
                    441.182
                ]
            ],
            "group_id": null,
            "description": "",
            "shape_type": "polygon",
            "flags": {},
            "mask": null
        },
        {
            "label": "wall",
            "points": [
                [
                    599.754,
                    529.053
                ],
                [
                    604.402,
                    610.47
                ],
                [
                    507.498,
                    617.874
                ],
                [
                    507.746,
                    625.905
                ],
                [
                    620.543,
                    617.422
                ],
                [
                    607.638,
                    426.169
                ],
                [
                    602.465,
                    426.731
                ],
                [
                    604.002,
                    451.585
                ],
                [
                    497.201,
                    458.663
                ],
                [
                    504.161,
                    549.087
                ],
                [
                    476.593,
                    550.513
                ],
                [
                    477.328,
                    559.584
                ],
                [
                    504.696,
                    558.172
                ],
                [
                    505.887,
                    576.474
                ],
                [
                    513.735,
                    575.521
                ],
                [
                    506.683,
                    484.549
                ],
                [
                    566.684,
                    479.795
                ],
                [
                    570.158,
                    531.103
                ],
                [
                    599.754,
                    529.053
                ]
            ],
            "group_id": null,
            "description": "",
            "shape_type": "polygon",
            "flags": {},
            "mask": null
        },
        {
            "label": "wall",
            "points": [
                [
                    505.2,
                    465.421
                ],
                [
                    600.787,
                    459.122
                ],
                [
                    605.13,
                    521.228
                ],
                [
                    577.156,
                    523.298
                ],
                [
                    573.479,
                    472.347
                ],
                [
                    506.038,
                    476.234
                ],
                [
                    505.2,
                    465.421
                ]
            ],
            "group_id": null,
            "description": "",
            "shape_type": "polygon",
            "flags": {},
            "mask": null
        },
        {
            "label": "wall",
            "points": [
                [
                    183.347,
                    576.27
                ],
                [
                    181.33,
                    549.051
                ],
                [
                    172.881,
                    549.982
                ],
                [
                    174.866,
                    576.749
                ],
                [
                    183.347,
                    576.27
                ]
            ],
            "group_id": null,
            "description": "",
            "shape_type": "polygon",
            "flags": {},
            "mask": null
        },
        {
            "label": "wall",
            "points": [
                [
                    175.38,
                    637.677
                ],
                [
                    142.447,
                    640.775
                ],
                [
                    135.494,
                    552.71
                ],
                [
                    119.549,
                    553.598
                ],
                [
                    125.354,
                    642.696
                ],
                [
                    74.039,
                    646.284
                ],
                [
                    71.657,
                    618.124
                ],
                [
                    61.248,
                    618.714
                ],
                [
                    63.542,
                    653.481
                ],
                [
                    187.42,
                    645.369
                ],
                [
                    185.249,
                    621.32
                ],
                [
                    173.943,
                    621.997
                ],
                [
                    175.38,
                    637.677
                ]
            ],
            "group_id": null,
            "description": "",
            "shape_type": "polygon",
            "flags": {},
            "mask": null
        },
        {
            "label": "wall",
            "points": [
                [
                    51.895,
                    556.777
                ],
                [
                    57.196,
                    556.607
                ],
                [
                    58.805,
                    576.744
                ],
                [
                    69.658,
                    575.684
                ],
                [
                    67.907,
                    554.956
                ],
                [
                    121.996,
                    551.475
                ],
                [
                    121.081,
                    544.12
                ],
                [
                    52.101,
                    548.242
                ],
                [
                    51.895,
                    556.777
                ]
            ],
            "group_id": null,
            "description": "",
            "shape_type": "polygon",
            "flags": {},
            "mask": null
        },
        {
            "label": "wall",
            "points": [
                [
                    843.065,
                    114.842
                ],
                [
                    845.854,
                    156.264
                ],
                [
                    859.9,
                    155.175
                ],
                [
                    856.63,
                    99.237
                ],
                [
                    647.125,
                    114.101
                ],
                [
                    648.063,
                    127.515
                ],
                [
                    843.065,
                    114.842
                ]
            ],
            "group_id": null,
            "description": "",
            "shape_type": "polygon",
            "flags": {},
            "mask": null
        },
        {
            "label": "wall",
            "points": [
                [
                    661.606,
                    240.049
                ],
                [
                    671.19,
                    239.379
                ],
                [
                    663.862,
                    134.578
                ],
                [
                    655.16,
                    135.187
                ],
                [
                    661.606,
                    240.049
                ]
            ],
            "group_id": null,
            "description": "",
            "shape_type": "polygon",
            "flags": {},
            "mask": null
        },
        {
            "label": "wall",
            "points": [
                [
                    858.615,
                    327.57
                ],
                [
                    872.006,
                    326.634
                ],
                [
                    865.401,
                    240.195
                ],
                [
                    852.13,
                    241.235
                ],
                [
                    858.615,
                    327.57
                ]
            ],
            "group_id": null,
            "description": "",
            "shape_type": "polygon",
            "flags": {},
            "mask": null
        },
        {
            "label": "wall",
            "points": [
                [
                    673.962,
                    285.43
                ],
                [
                    664.896,
                    285.924
                ],
                [
                    673.88,
                    420.401
                ],
                [
                    684.737,
                    419.502
                ],
                [
                    675.627,
                    297.41
                ],
                [
                    847.97,
                    285.163
                ],
                [
                    846.718,
                    277.27
                ],
                [
                    674.283,
                    290.028
                ],
                [
                    673.962,
                    285.43
                ]
            ],
            "group_id": null,
            "description": "",
            "shape_type": "polygon",
            "flags": {},
            "mask": null
        },
        {
            "label": "wall",
            "points": [
                [
                    677.204,
                    484.506
                ],
                [
                    725.388,
                    480.974
                ],
                [
                    732.282,
                    565.688
                ],
                [
                    694.265,
                    568.71
                ],
                [
                    691.492,
                    530.797
                ],
                [
                    681.348,
                    531.506
                ],
                [
                    685.108,
                    578.331
                ],
                [
                    741.603,
                    574.017
                ],
                [
                    738.42,
                    533.705
                ],
                [
                    863.538,
                    524.955
                ],
                [
                    862.697,
                    516.398
                ],
                [
                    737.691,
                    525.018
                ],
                [
                    733.971,
                    480.495
                ],
                [
                    778.763,
                    477.404
                ],
                [
                    777.413,
                    461.556
                ],
                [
                    676.273,
                    469.474
                ],
                [
                    677.204,
                    484.506
                ]
            ],
            "group_id": null,
            "description": "",
            "shape_type": "polygon",
            "flags": {},
            "mask": null
        },
        {
            "label": "wall",
            "points": [
                [
                    824.757,
                    468.001
                ],
                [
                    860.042,
                    465.876
                ],
                [
                    859.202,
                    457.134
                ],
                [
                    824.639,
                    459.779
                ],
                [
                    824.757,
                    468.001
                ]
            ],
            "group_id": null,
            "description": "",
            "shape_type": "polygon",
            "flags": {},
            "mask": null
        },
        {
            "label": "wall",
            "points": [
                [
                    863.282,
                    523.032
                ],
                [
                    965.788,
                    517.199
                ],
                [
                    964.998,
                    509.365
                ],
                [
                    869.839,
                    516.141
                ],
                [
                    867.968,
                    492.849
                ],
                [
                    861.213,
                    493.443
                ],
                [
                    863.282,
                    523.032
                ]
            ],
            "group_id": null,
            "description": "",
            "shape_type": "polygon",
            "flags": {},
            "mask": null
        },
        {
            "label": "wall",
            "points": [
                [
                    869.19,
                    485.705
                ],
                [
                    969.301,
                    479.421
                ],
                [
                    976.495,
                    564.739
                ],
                [
                    990.332,
                    563.669
                ],
                [
                    982.949,
                    463.941
                ],
                [
                    882.248,
                    470.574
                ],
                [
                    878.346,
                    410.393
                ],
                [
                    864.436,
                    411.877
                ],
                [
                    869.19,
                    485.705
                ]
            ],
            "group_id": null,
            "description": "",
            "shape_type": "polygon",
            "flags": {},
            "mask": null
        },
        {
            "label": "wall",
            "points": [
                [
                    869.573,
                    736.109
                ],
                [
                    884.959,
                    734.736
                ],
                [
                    878.545,
                    637.715
                ],
                [
                    862.37,
                    638.737
                ],
                [
                    869.573,
                    736.109
                ]
            ],
            "group_id": null,
            "description": "",
            "shape_type": "polygon",
            "flags": {},
            "mask": null
        },
        {
            "label": "wall",
            "points": [
                [
                    973.244,
                    639.975
                ],
                [
                    972.746,
                    630.859
                ],
                [
                    926.71,
                    634.771
                ],
                [
                    927.574,
                    643.168
                ],
                [
                    973.244,
                    639.975
                ]
            ],
            "group_id": null,
            "description": "",
            "shape_type": "polygon",
            "flags": {},
            "mask": null
        },
        {
            "label": "wall",
            "points": [
                [
                    988.969,
                    750.877
                ],
                [
                    958.319,
                    753.663
                ],
                [
                    959.634,
                    767.868
                ],
                [
                    1004.055,
                    764.441
                ],
                [
                    993.821,
                    613.505
                ],
                [
                    979.445,
                    614.671
                ],
                [
                    988.969,
                    750.877
                ]
            ],
            "group_id": null,
            "description": "",
            "shape_type": "polygon",
            "flags": {},
            "mask": null
        },
        {
            "label": "wall",
            "points": [
                [
                    889.439,
                    885.203
                ],
                [
                    845.726,
                    888.467
                ],
                [
                    846.887,
                    902.098
                ],
                [
                    904.674,
                    898.057
                ],
                [
                    895.773,
                    772.258
                ],
                [
                    908.267,
                    771.176
                ],
                [
                    907.276,
                    757.014
                ],
                [
                    880.281,
                    758.694
                ],
                [
                    889.439,
                    885.203
                ]
            ],
            "group_id": null,
            "description": "",
            "shape_type": "polygon",
            "flags": {},
            "mask": null
        },
        {
            "label": "wall",
            "points": [
                [
                    618.591,
                    814.403
                ],
                [
                    634.046,
                    813.683
                ],
                [
                    625.912,
                    674.162
                ],
                [
                    608.726,
                    675.905
                ],
                [
                    618.591,
                    814.403
                ]
            ],
            "group_id": null,
            "description": "",
            "shape_type": "polygon",
            "flags": {},
            "mask": null
        },
        {
            "label": "wall",
            "points": [
                [
                    604.645,
                    832.061
                ],
                [
                    620.086,
                    830.982
                ],
                [
                    625.294,
                    904.2
                ],
                [
                    616.087,
                    905.236
                ],
                [
                    616.997,
                    918.242
                ],
                [
                    675.255,
                    914.037
                ],
                [
                    674.019,
                    901.969
                ],
                [
                    633.022,
                    904.444
                ],
                [
                    626.615,
                    822.161
                ],
                [
                    604.532,
                    824.097
                ],
                [
                    604.645,
                    832.061
                ]
            ],
            "group_id": null,
            "description": "",
            "shape_type": "polygon",
            "flags": {},
            "mask": null
        },
        {
            "label": "wall",
            "points": [
                [
                    532.538,
                    924.165
                ],
                [
                    531.467,
                    908.86
                ],
                [
                    495.655,
                    911.227
                ],
                [
                    496.697,
                    926.122
                ],
                [
                    532.538,
                    924.165
                ]
            ],
            "group_id": null,
            "description": "",
            "shape_type": "polygon",
            "flags": {},
            "mask": null
        },
        {
            "label": "wall",
            "points": [
                [
                    208.245,
                    721.079
                ],
                [
                    222.331,
                    922.51
                ],
                [
                    232.18,
                    922.464
                ],
                [
                    217.196,
                    711.243
                ],
                [
                    103.401,
                    719.628
                ],
                [
                    104.176,
                    730.712
                ],
                [
                    208.245,
                    721.079
                ]
            ],
            "group_id": null,
            "description": "",
            "shape_type": "polygon",
            "flags": {},
            "mask": null
        },
        {
            "label": "wall",
            "points": [
                [
                    277.349,
                    942.049
                ],
                [
                    276.169,
                    928.009
                ],
                [
                    186.111,
                    934.307
                ],
                [
                    187.701,
                    948.516
                ],
                [
                    277.349,
                    942.049
                ]
            ],
            "group_id": null,
            "description": "",
            "shape_type": "polygon",
            "flags": {},
            "mask": null
        },
        {
            "label": "wall",
            "points": [
                [
                    58.023,
                    942.866
                ],
                [
                    59.088,
                    958.106
                ],
                [
                    104.373,
                    954.343
                ],
                [
                    103.574,
                    940.078
                ],
                [
                    58.023,
                    942.866
                ]
            ],
            "group_id": null,
            "description": "",
            "shape_type": "polygon",
            "flags": {},
            "mask": null
        },
        {
            "label": "stairs",
            "points": [
                [
                    369.388,
                    155.977
                ],
                [
                    361.413,
                    29.233
                ],
                [
                    106.632,
                    45.719
                ],
                [
                    115.994,
                    173.252
                ],
                [
                    369.388,
                    155.977
                ]
            ],
            "group_id": null,
            "description": "",
            "shape_type": "polygon",
            "flags": {},
            "mask": null
        },
        {
            "label": "elevator",
            "points": [
                [
                    255.094,
                    313.496
                ],
                [
                    245.565,
                    182.454
                ],
                [
                    114.473,
                    191.255
                ],
                [
                    126.576,
                    322.483
                ],
                [
                    255.094,
                    313.496
                ]
            ],
            "group_id": null,
            "description": "",
            "shape_type": "polygon",
            "flags": {},
            "mask": null
        },
        {
            "label": "others",
            "points": [
                [
                    126.885,
                    339.578
                ],
                [
                    130.619,
                    392.983
                ],
                [
                    149.694,
                    390.637
                ],
                [
                    166.334,
                    404.155
                ],
                [
                    176.008,
                    528.024
                ],
                [
                    270.762,
                    521.905
                ],
                [
                    267.52,
                    475.553
                ],
                [
                    284.753,
                    454.097
                ],
                [
                    489.702,
                    438.247
                ],
                [
                    483.314,
                    354.144
                ],
                [
                    401.121,
                    358.879
                ],
                [
                    383.368,
                    343.919
                ],
                [
                    371.964,
                    173.593
                ],
                [
                    259.143,
                    181.988
                ],
                [
                    271.411,
                    328.459
                ],
                [
                    126.885,
                    339.578
                ]
            ],
            "group_id": null,
            "description": "",
            "shape_type": "polygon",
            "flags": {},
            "mask": null
        },
        {
            "label": "bathroom",
            "points": [
                [
                    584.674,
                    317.1
                ],
                [
                    577.216,
                    226.829
                ],
                [
                    455.759,
                    234.749
                ],
                [
                    461.752,
                    324.55
                ],
                [
                    584.674,
                    317.1
                ]
            ],
            "group_id": null,
            "description": "",
            "shape_type": "polygon",
            "flags": {},
            "mask": null
        },
        {
            "label": "bathroom",
            "points": [
                [
                    516.219,
                    616.999
                ],
                [
                    603.72,
                    609.687
                ],
                [
                    600.213,
                    529.677
                ],
                [
                    570.082,
                    529.696
                ],
                [
                    566.214,
                    478.651
                ],
                [
                    506.621,
                    484.011
                ],
                [
                    516.219,
                    616.999
                ]
            ],
            "group_id": null,
            "description": "",
            "shape_type": "polygon",
            "flags": {},
            "mask": null
        },
        {
            "label": "bathroom",
            "points": [
                [
                    294.17,
                    706.524
                ],
                [
                    387.142,
                    698.623
                ],
                [
                    377.682,
                    543.318
                ],
                [
                    282.144,
                    550.558
                ],
                [
                    294.17,
                    706.524
                ]
            ],
            "group_id": null,
            "description": "",
            "shape_type": "polygon",
            "flags": {},
            "mask": null
        },
        {
            "label": "others",
            "points": [
                [
                    886.493,
                    749.774
                ],
                [
                    980.66,
                    743.681
                ],
                [
                    972.905,
                    639.802
                ],
                [
                    880.256,
                    646.526
                ],
                [
                    886.493,
                    749.774
                ]
            ],
            "group_id": null,
            "description": "",
            "shape_type": "polygon",
            "flags": {},
            "mask": null
        },
        {
            "label": "dressing_room",
            "points": [
                [
                    503.992,
                    548.519
                ],
                [
                    496.94,
                    459.696
                ],
                [
                    388.249,
                    468.137
                ],
                [
                    395.87,
                    556.08
                ],
                [
                    503.992,
                    548.519
                ]
            ],
            "group_id": null,
            "description": "",
            "shape_type": "polygon",
            "flags": {},
            "mask": null
        },
        {
            "label": "dressing_room",
            "points": [
                [
                    861.475,
                    516.119
                ],
                [
                    858.589,
                    471.134
                ],
                [
                    734.539,
                    479.808
                ],
                [
                    738.459,
                    524.722
                ],
                [
                    861.475,
                    516.119
                ]
            ],
            "group_id": null,
            "description": "",
            "shape_type": "polygon",
            "flags": {},
            "mask": null
        },
        {
            "label": "others",
            "points": [
                [
                    694.225,
                    568.068
                ],
                [
                    732.492,
                    565.652
                ],
                [
                    725.825,
                    481.456
                ],
                [
                    687.835,
                    484.113
                ],
                [
                    694.225,
                    568.068
                ]
            ],
            "group_id": null,
            "description": "",
            "shape_type": "polygon",
            "flags": {},
            "mask": null
        },
        {
            "label": "bed_room",
            "points": [
                [
                    858.763,
                    456.051
                ],
                [
                    846.333,
                    284.781
                ],
                [
                    675.499,
                    296.954
                ],
                [
                    688.365,
                    467.966
                ],
                [
                    858.763,
                    456.051
                ]
            ],
            "group_id": null,
            "description": "",
            "shape_type": "polygon",
            "flags": {},
            "mask": null
        },
        {
            "label": "bed_room",
            "points": [
                [
                    844.427,
                    276.977
                ],
                [
                    835.081,
                    123.862
                ],
                [
                    664.409,
                    135.116
                ],
                [
                    674.012,
                    288.667
                ],
                [
                    844.427,
                    276.977
                ]
            ],
            "group_id": null,
            "description": "",
            "shape_type": "polygon",
            "flags": {},
            "mask": null
        },
        {
            "label": "entrance",
            "points": [
                [
                    603.297,
                    450.417
                ],
                [
                    595.291,
                    331.92
                ],
                [
                    504.912,
                    340.486
                ],
                [
                    512.027,
                    454.272
                ],
                [
                    603.297,
                    450.417
                ]
            ],
            "group_id": null,
            "description": "",
            "shape_type": "polygon",
            "flags": {},
            "mask": null
        },
        {
            "label": "bed_room",
            "points": [
                [
                    413.595,
                    829.526
                ],
                [
                    619.389,
                    815.135
                ],
                [
                    604.425,
                    622.376
                ],
                [
                    400.693,
                    634.395
                ],
                [
                    413.595,
                    829.526
                ]
            ],
            "group_id": null,
            "description": "",
            "shape_type": "polygon",
            "flags": {},
            "mask": null
        },
        {
            "label": "bed_room",
            "points": [
                [
                    231.285,
                    921.125
                ],
                [
                    402.497,
                    910.103
                ],
                [
                    388.479,
                    709.645
                ],
                [
                    217.641,
                    719.216
                ],
                [
                    231.285,
                    921.125
                ]
            ],
            "group_id": null,
            "description": "",
            "shape_type": "polygon",
            "flags": {},
            "mask": null
        },
        {
            "label": "bed_room",
            "points": [
                [
                    69.022,
                    931.047
                ],
                [
                    221.257,
                    920.401
                ],
                [
                    208.45,
                    723.659
                ],
                [
                    55.104,
                    732.007
                ],
                [
                    69.022,
                    931.047
                ]
            ],
            "group_id": null,
            "description": "",
            "shape_type": "polygon",
            "flags": {},
            "mask": null
        },
        {
            "label": "entrance",
            "points": [
                [
                    255.958,
                    640.953
                ],
                [
                    255.628,
                    633.425
                ],
                [
                    279.815,
                    633.289
                ],
                [
                    274.754,
                    551.028
                ],
                [
                    250.847,
                    552.7
                ],
                [
                    250.165,
                    544.327
                ],
                [
                    242.811,
                    544.841
                ],
                [
                    242.364,
                    538.446
                ],
                [
                    179.927,
                    541.527
                ],
                [
                    187.491,
                    645.098
                ],
                [
                    255.958,
                    640.953
                ]
            ],
            "group_id": null,
            "description": "",
            "shape_type": "polygon",
            "flags": {},
            "mask": null
        },
        {
            "label": "living_kitchen",
            "points": [
                [
                    638.826,
                    895.55
                ],
                [
                    880.097,
                    877.405
                ],
                [
                    862.856,
                    636.92
                ],
                [
                    972.728,
                    628.812
                ],
                [
                    962.9,
                    518.636
                ],
                [
                    737.996,
                    533.938
                ],
                [
                    742.19,
                    575.696
                ],
                [
                    683.799,
                    578.93
                ],
                [
                    658.683,
                    213.691
                ],
                [
                    593.106,
                    217.427
                ],
                [
                    638.826,
                    895.55
                ]
            ],
            "group_id": null,
            "description": "",
            "shape_type": "polygon",
            "flags": {},
            "mask": null
        },
        {
            "label": "others",
            "points": [
                [
                    445.208,
                    178.98
                ],
                [
                    504.936,
                    175.042
                ],
                [
                    507.76,
                    222.228
                ],
                [
                    660.235,
                    213.233
                ],
                [
                    654.663,
                    136.951
                ],
                [
                    443.826,
                    152.409
                ],
                [
                    445.208,
                    178.98
                ]
            ],
            "group_id": null,
            "description": "",
            "shape_type": "polygon",
            "flags": {},
            "mask": null
        },
        {
            "label": "others",
            "points": [
                [
                    498.822,
                    223.806
                ],
                [
                    496.628,
                    185.623
                ],
                [
                    446.108,
                    188.442
                ],
                [
                    448.169,
                    224.729
                ],
                [
                    498.822,
                    223.806
                ]
            ],
            "group_id": null,
            "description": "",
            "shape_type": "polygon",
            "flags": {},
            "mask": null
        },
        {
            "label": "others",
            "points": [
                [
                    422.418,
                    151.157
                ],
                [
                    414.298,
                    26.849
                ],
                [
                    363.277,
                    31.244
                ],
                [
                    373.884,
                    154.739
                ],
                [
                    422.418,
                    151.157
                ]
            ],
            "group_id": null,
            "description": "",
            "shape_type": "polygon",
            "flags": {},
            "mask": null
        },
        {
            "label": "others",
            "points": [
                [
                    428.632,
                    914.686
                ],
                [
                    517.614,
                    908.194
                ],
                [
                    513.513,
                    837.958
                ],
                [
                    423.187,
                    844.545
                ],
                [
                    428.632,
                    914.686
                ]
            ],
            "group_id": null,
            "description": "",
            "shape_type": "polygon",
            "flags": {},
            "mask": null
        },
        {
            "label": "balcony",
            "points": [
                [
                    532.803,
                    909.023
                ],
                [
                    625.687,
                    900.366
                ],
                [
                    619.761,
                    831.069
                ],
                [
                    525.826,
                    836.287
                ],
                [
                    532.803,
                    909.023
                ]
            ],
            "group_id": null,
            "description": "",
            "shape_type": "polygon",
            "flags": {},
            "mask": null
        },
        {
            "label": "others",
            "points": [
                [
                    74.945,
                    646.216
                ],
                [
                    125.137,
                    641.974
                ],
                [
                    119.187,
                    551.659
                ],
                [
                    67.852,
                    555.248
                ],
                [
                    74.945,
                    646.216
                ]
            ],
            "group_id": null,
            "description": "",
            "shape_type": "polygon",
            "flags": {},
            "mask": null
        },
        {
            "label": "others",
            "points": [
                [
                    175.265,
                    637.206
                ],
                [
                    172.032,
                    550.6
                ],
                [
                    134.865,
                    554.141
                ],
                [
                    142.296,
                    640.217
                ],
                [
                    175.265,
                    637.206
                ]
            ],
            "group_id": null,
            "description": "",
            "shape_type": "polygon",
            "flags": {},
            "mask": null
        },
        {
            "label": "others",
            "points": [
                [
                    117.949,
                    488.63
                ],
                [
                    27.675,
                    492.023
                ],
                [
                    31.348,
                    549.187
                ],
                [
                    121.697,
                    542.221
                ],
                [
                    117.949,
                    488.63
                ]
            ],
            "group_id": null,
            "description": "",
            "shape_type": "polygon",
            "flags": {},
            "mask": null
        },
        {
            "label": "others",
            "points": [
                [
                    141.052,
                    532.843
                ],
                [
                    172.829,
                    529.366
                ],
                [
                    165.152,
                    410.614
                ],
                [
                    147.472,
                    397.201
                ],
                [
                    131.349,
                    397.073
                ],
                [
                    141.052,
                    532.843
                ]
            ],
            "group_id": null,
            "description": "",
            "shape_type": "polygon",
            "flags": {},
            "mask": null
        },
        {
            "label": "others",
            "points": [
                [
                    272.905,
                    497.045
                ],
                [
                    368.138,
                    491.223
                ],
                [
                    365.115,
                    453.973
                ],
                [
                    284.771,
                    460.219
                ],
                [
                    271.585,
                    475.163
                ],
                [
                    272.905,
                    497.045
                ]
            ],
            "group_id": null,
            "description": "",
            "shape_type": "polygon",
            "flags": {},
            "mask": null
        },
        {
            "label": "others",
            "points": [
                [
                    377.144,
                    536.216
                ],
                [
                    374.908,
                    510.212
                ],
                [
                    290.485,
                    517.999
                ],
                [
                    291.55,
                    542.201
                ],
                [
                    377.144,
                    536.216
                ]
            ],
            "group_id": null,
            "description": "",
            "shape_type": "polygon",
            "flags": {},
            "mask": null
        },
        {
            "label": "others",
            "points": [
                [
                    400.987,
                    625.899
                ],
                [
                    507.36,
                    618.728
                ],
                [
                    503.823,
                    558.073
                ],
                [
                    395.641,
                    563.437
                ],
                [
                    400.987,
                    625.899
                ]
            ],
            "group_id": null,
            "description": "",
            "shape_type": "polygon",
            "flags": {},
            "mask": null
        },
        {
            "label": "wall",
            "points": [
                [
                    433.07,
                    623.487
                ],
                [
                    399.198,
                    625.444
                ],
                [
                    399.51,
                    631.867
                ],
                [
                    433.157,
                    630.611
                ],
                [
                    433.07,
                    623.487
                ]
            ],
            "group_id": null,
            "description": "",
            "shape_type": "polygon",
            "flags": {},
            "mask": null
        },
        {
            "label": "others",
            "points": [
                [
                    573.764,
                    472.1
                ],
                [
                    577.791,
                    523.55
                ],
                [
                    605.339,
                    521.517
                ],
                [
                    600.757,
                    459.05
                ],
                [
                    505.784,
                    465.37
                ],
                [
                    506.469,
                    476.698
                ],
                [
                    573.764,
                    472.1
                ]
            ],
            "group_id": null,
            "description": "",
            "shape_type": "polygon",
            "flags": {},
            "mask": null
        },
        {
            "label": "others",
            "points": [
                [
                    963.773,
                    509.708
                ],
                [
                    962.903,
                    487.179
                ],
                [
                    868.077,
                    493.986
                ],
                [
                    869.849,
                    516.806
                ],
                [
                    963.773,
                    509.708
                ]
            ],
            "group_id": null,
            "description": "",
            "shape_type": "polygon",
            "flags": {},
            "mask": null
        },
        {
            "label": "others",
            "points": [
                [
                    386.296,
                    341.76
                ],
                [
                    402.001,
                    355.413
                ],
                [
                    436.988,
                    352.063
                ],
                [
                    425.15,
                    169.863
                ],
                [
                    373.408,
                    174.685
                ],
                [
                    386.296,
                    341.76
                ]
            ],
            "group_id": null,
            "description": "",
            "shape_type": "polygon",
            "flags": {},
            "mask": null
        },
        {
            "label": "background",
            "points": [
                [
                    495.168,
                    0.0
                ],
                [
                    0.0,
                    34.626
                ],
                [
                    0.0,
                    386.921
                ],
                [
                    36.739,
                    384.316
                ],
                [
                    43.603,
                    469.091
                ],
                [
                    117.451,
                    466.738
                ],
                [
                    86.396,
                    45.033
                ],
                [
                    432.937,
                    21.878
                ],
                [
                    439.365,
                    129.218
                ],
                [
                    856.4,
                    96.823
                ],
                [
                    883.651,
                    471.102
                ],
                [
                    982.334,
                    464.202
                ],
                [
                    1004.634,
                    767.686
                ],
                [
                    899.514,
                    775.037
                ],
                [
                    905.072,
                    900.762
                ],
                [
                    56.831,
                    963.311
                ],
                [
                    42.075,
                    723.282
                ],
                [
                    285.315,
                    705.552
                ],
                [
                    281.416,
                    639.476
                ],
                [
                    62.626,
                    656.217
                ],
                [
                    57.287,
                    559.231
                ],
                [
                    47.039,
                    557.063
                ],
                [
                    47.872,
                    548.351
                ],
                [
                    29.93,
                    549.605
                ],
                [
                    17.821,
                    386.744
                ],
                [
                    0.0,
                    387.731
                ],
                [
                    0.0,
                    499.405
                ],
                [
                    32.626,
                    964.0
                ],
                [
                    514.496,
                    964.0
                ],
                [
                    1024.0,
                    928.372
                ],
                [
                    1024.0,
                    478.456
                ],
                [
                    990.543,
                    0.0
                ],
                [
                    495.168,
                    0.0
                ]
            ],
            "group_id": null,
            "description": "",
            "shape_type": "polygon",
            "flags": {},
            "mask": null
        }
    ],
    "imagePath": "..\\images\\TE_D_00030_png.rf.34cb7fc9a97fb14bdea598dd975d126b.jpg",
    "imageData": null,
    "imageHeight": 964,
    "imageWidth": 1024
}